ScikitAndTensorflowWorkbooksBjpcjp/README.md
ScikitAndTensorflowWorkbooksBjpcjp/__init__.py
ScikitAndTensorflowWorkbooksBjpcjp/__main__.py
ScikitAndTensorflowWorkbooksBjpcjp/file.epub
ScikitAndTensorflowWorkbooksBjpcjp/index.html
ScikitAndTensorflowWorkbooksBjpcjp/css/__init__.py
ScikitAndTensorflowWorkbooksBjpcjp/css/annotations.css
ScikitAndTensorflowWorkbooksBjpcjp/css/main.css
ScikitAndTensorflowWorkbooksBjpcjp/css/normalize.css
ScikitAndTensorflowWorkbooksBjpcjp/css/popup.css
ScikitAndTensorflowWorkbooksBjpcjp/font/__init__.py
ScikitAndTensorflowWorkbooksBjpcjp/font/fontello.eot
ScikitAndTensorflowWorkbooksBjpcjp/font/fontello.svg
ScikitAndTensorflowWorkbooksBjpcjp/font/fontello.ttf
ScikitAndTensorflowWorkbooksBjpcjp/font/fontello.woff
ScikitAndTensorflowWorkbooksBjpcjp/img/__init__.py
ScikitAndTensorflowWorkbooksBjpcjp/img/annotator-glyph-sprite.png
ScikitAndTensorflowWorkbooksBjpcjp/img/annotator-icon-sprite.png
ScikitAndTensorflowWorkbooksBjpcjp/img/apple-touch-icon.png
ScikitAndTensorflowWorkbooksBjpcjp/img/cancelfullscreen.png
ScikitAndTensorflowWorkbooksBjpcjp/img/close.png
ScikitAndTensorflowWorkbooksBjpcjp/img/fullscreen.png
ScikitAndTensorflowWorkbooksBjpcjp/img/loader.gif
ScikitAndTensorflowWorkbooksBjpcjp/img/menu-icon.png
ScikitAndTensorflowWorkbooksBjpcjp/img/save.png
ScikitAndTensorflowWorkbooksBjpcjp/img/saved.png
ScikitAndTensorflowWorkbooksBjpcjp/img/settings-s.png
ScikitAndTensorflowWorkbooksBjpcjp/img/settings.png
ScikitAndTensorflowWorkbooksBjpcjp/img/star.png
ScikitAndTensorflowWorkbooksBjpcjp/js/__init__.py
ScikitAndTensorflowWorkbooksBjpcjp/js/epub.js
ScikitAndTensorflowWorkbooksBjpcjp/js/epub.min.js
ScikitAndTensorflowWorkbooksBjpcjp/js/epub.min.map
ScikitAndTensorflowWorkbooksBjpcjp/js/hooks.min.js
ScikitAndTensorflowWorkbooksBjpcjp/js/hooks.min.map
ScikitAndTensorflowWorkbooksBjpcjp/js/reader.js
ScikitAndTensorflowWorkbooksBjpcjp/js/reader.js.map
ScikitAndTensorflowWorkbooksBjpcjp/js/reader.min.js
scikit_and_tensorflow_workbooks_bjpcjp-2024.3.3.0.dist-info/METADATA
scikit_and_tensorflow_workbooks_bjpcjp-2024.3.3.0.dist-info/WHEEL
scikit_and_tensorflow_workbooks_bjpcjp-2024.3.3.0.dist-info/entry_points.txt
scikit_and_tensorflow_workbooks_bjpcjp-2024.3.3.0.dist-info/top_level.txt
scikit_and_tensorflow_workbooks_bjpcjp-2024.3.3.0.dist-info/RECORD
